{"is_source_file": true, "format": "Dart", "description": "Defines routing logic for a Flutter app, mapping route names to corresponding pages such as event form, birthday form, and chat page.", "external_files": ["../features/birthdays/birthday_form_page.dart", "../features/events/event_form_page.dart", "../features/messages/chat_page.dart"], "external_methods": ["MaterialPageRoute.builder", "Scaffold", "AppBar", "Center", "Text"], "published": ["AppRouter"], "classes": [{"name": "AppRouter", "description": "Contains static method for handling route generation based on route name."}], "methods": [{"name": "onGenerateRoute", "description": "Generates routes based on the provided RouteSettings, returning appropriate page or default error page."}], "calls": ["MaterialPageRoute.builder", "Scaffold", "AppBar", "Center", "Text"], "search-terms": ["route handling", "navigation", "/eventForm", "/birthdayForm", "/chat", "named routes", "Flutter routing"], "state": 2, "file_id": 48, "knowledge_revision": 124, "git_revision": "", "hash": "57030f50013de80b5123c3940fdeb99c", "format-version": 4, "code-base-name": "event_manager_frontend", "filename": "event_manager_frontend/lib/routing/app_router.dart", "revision_history": [{"124": ""}]}